Workbook

Sheet DASHBOARD
B2: ARÇELİK A.Ş. — KPI Dashboard
B3: Finansal Performans Karşılaştırması | 2024 vs 2025 | Kaynak: KAP Konsolide Tablolar
B6: ✅ | C6: Brüt Kar Marjı | E6: ❌ | F6: Net Kar Marjı | H6: ⚠️ | I6: DSO | K6: ✅ | L6: CCC | N6: ⚠️ | O6: A/P Devir Oranı
B7: ='2. KPI Hesaplamalari'!D5 -> 0.28781003 | E7: ='2. KPI Hesaplamalari'!D6 -> -0.018703359 | H7: ='2. KPI Hesaplamalari'!D9 -> 81.238747 | K7: ='2. KPI Hesaplamalari'!D11 -> 41.736891 | N7: ='2. KPI Hesaplamalari'!D12 -> 2.862315
B8: ='2. KPI Hesaplamalari'!F5 -> 1.2224 | C8: (Gross Margin) | E8: ='2. KPI Hesaplamalari'!F6 -> -1.3553 | F8: (Net Margin) | H8: ='2. KPI Hesaplamalari'!F9 -> 2.0916713 | I8: (Days Sales Outstanding) | K8: ='2. KPI Hesaplamalari'!F11 -> -1.35513 | L8: (Cash Conversion Cycle) | N8: ='2. KPI Hesaplamalari'!F12 -> -0.16969427 | O8: (A/P Turnover)
B50: 💡 ANAHTAR BULGULAR / KEY INSIGHTS
B51: ✅ | C51: Brüt marj iyileşti (%27.6 → %28.8) | H51: Üretim verimliliği güçleniyor — temel iş sağlıklı.
B52: ❌ | C52: Net zarar derinleşti (-2.9 → -9.8 milyar TL) | H52: 47.6 milyar TL finansman gideri faaliyet karını eritiyor.
B53: ⚠️ | C53: Cari oran 0.97 (1'in altında) | H53: Kısa vadeli yükümlülükler kısa vadeli varlıkları aştı — likidite riski.
B54: ⚠️ | C54: Kısa vadeli borç +%71 arttı | H54: 67 → 115 milyar TL. Faiz baskısı sürdürülemez seviyede.
B55: ✅ | C55: CCC kısaldı (43 → 41.7 gün) | H55: İşletme sermayesi verimliliği hafif iyileşti.
B56: ⚠️ | C56: Stok süresi 88 gün (yüksek) | H56: Sektör ortalaması 60-70 gün — 18 milyar TL nakit serbest kalabilir.
B58: Hazırlayan: Iryna | Kaynak: ARCLK 2025 Konsolide Finansal Tablolar (KAP) | Birim: Bin TL ve %
A80: KPI | B80: 2024 | C80: 2025
A81: Brüt Kar Marjı | B81: ='2. KPI Hesaplamalari'!E5 -> 0.27558634 | C81: ='2. KPI Hesaplamalari'!D5 -> 0.28781003
A82: Net Kar Marjı | B82: ='2. KPI Hesaplamalari'!E6 -> -0.0051506181 | C82: ='2. KPI Hesaplamalari'!D6 -> -0.018703359
A90: Metric | B90: 2024 | C90: 2025
A91: DIO (Stok) | B91: ='2. KPI Hesaplamalari'!E8 -> 84.327163 | C91: ='2. KPI Hesaplamalari'!D8 -> 88.017303
A92: DSO (Alacak) | B92: ='2. KPI Hesaplamalari'!E9 -> 79.147076 | C92: ='2. KPI Hesaplamalari'!D9 -> 81.238747
A93: DPO (Borç) | B93: ='2. KPI Hesaplamalari'!E10 -> 120.38222 | C93: ='2. KPI Hesaplamalari'!D10 -> 127.51916
A94: CCC | B94: ='2. KPI Hesaplamalari'!E11 -> 43.09202 | C94: ='2. KPI Hesaplamalari'!D11 -> 41.736891
A100: Kategori | B100: Tutar (Bin TL)
A101: ="Satışların Maliyeti ("&FIXED(B101/'1. Ham Veri (Raw Data)'!$C$6*100,1)&"%)" -> Satışların Maliyeti (71.2%) | B101: ='1. Ham Veri (Raw Data)'!C7 -> 373140054
A102: ="Pazarlama Giderleri ("&FIXED(B102/'1. Ham Veri (Raw Data)'!$C$6*100,1)&"%)" -> Pazarlama Giderleri (19.8%) | B102: ='1. Ham Veri (Raw Data)'!C9 -> 103927285
A103: ="G&A + Ar-Ge ("&FIXED(B103/'1. Ham Veri (Raw Data)'!$C$6*100,1)&"%)" -> G&A + Ar-Ge (7.6%) | B103: ='1. Ham Veri (Raw Data)'!C10+'1. Ham Veri (Raw Data)'!C11 -> 39870659
A104: ="Faaliyet Marjı (diğer gelirler hariç) ("&FIXED(B104/'1. Ham Veri (Raw Data)'!$C$6*100,1)&"%)" -> Faaliyet Marjı (diğer gelirler hariç) (1.3%) | B104: ='1. Ham Veri (Raw Data)'!C6-'1. Ham Veri (Raw Data)'!C7-'1. Ham Veri (Raw Data)'!C9-'1. Ham Veri (Raw Data)'!C10-'1. Ham Veri (Raw Data)'!C11 -> 6995323
A105: Not: Raporlanan esas faaliyet karı (10.5 milyar TL), 3.5 milyar TL net diğer faaliyet gelirini içerir; grafik yalnızca hasılattan düşülen giderleri gösterir.
A110: Kalem | B110: 2024 (Milyar TL) | C110: 2025 (Milyar TL)
A111: Hasılat | B111: ='1. Ham Veri (Raw Data)'!D6/1000000 -> 560.93675 | C111: ='1. Ham Veri (Raw Data)'!C6/1000000 -> 523.93332
A112: Brüt Kar | B112: ='1. Ham Veri (Raw Data)'!D8/1000000 -> 154.58651 | C112: ='1. Ham Veri (Raw Data)'!C8/1000000 -> 150.79327
A113: Faaliyet Karı | B113: ='1. Ham Veri (Raw Data)'!D12/1000000 -> 9.32271 | C113: ='1. Ham Veri (Raw Data)'!C12/1000000 -> 10.494106
A114: Net Kar (Zarar) | B114: ='1. Ham Veri (Raw Data)'!D14/1000000 -> -2.889171 | C114: ='1. Ham Veri (Raw Data)'!C14/1000000 -> -9.799313

Sheet 1. Ham Veri (Raw Data)
A1: ARÇELİK A.Ş. — Finansal Veriler / Financial Data
A2: Kaynak: ARCLK 2025 Yılsonu Konsolide Finansal Tablolar (KAP) | Birim: Bin TL
A4: Kalem / Item | B4: İngilizce / English | C4: 2025 | D4: 2024
A5: GELİR TABLOSU | B5: INCOME STATEMENT
A6: Hasılat | B6: Revenue | C6: 523933321 | D6: 560936754
A7: Satışların Maliyeti (-) | B7: Cost of Goods Sold (COGS) | C7: 373140054 | D7: 406350247
A8: Brüt Kar | B8: Gross Profit | C8: 150793267 | D8: 154586507
A9: Pazarlama Giderleri (-) | B9: Marketing Expenses | C9: 103927285 | D9: 108281560
A10: Genel Yönetim Giderleri (-) | B10: G&A Expenses | C10: 33379774 | D10: 32435620
A11: Ar-Ge Giderleri (-) | B11: R&D Expenses | C11: 6490885 | D11: 6346498
A12: Esas Faaliyet Karı | B12: Operating Profit | C12: 10494106 | D12: 9322710
A13: Finansman Giderleri (-) | B13: Financing Expenses | C13: 47635992 | D13: 61910541
A14: Net Dönem Karı / Zararı | B14: Net Income (Loss) | C14: -9799313 | D14: -2889171
A15: BİLANÇO | B15: BALANCE SHEET
A16: Nakit ve Nakit Benzerleri | B16: Cash & Cash Equivalents | C16: 97829154 | D16: 66514006
A17: Ticari Alacaklar (KV) | B17: Trade Receivables (ST) | C17: 116612840 | D17: 121634257
A18: Stoklar | B18: Inventory | C18: 89980222 | D18: 93880448
A19: Dönen Varlıklar Toplamı | B19: Total Current Assets | C19: 330746728 | D19: 300353563
A20: Toplam Varlıklar | B20: Total Assets | C20: 543531612 | D20: 520592827
A21: Ticari Borçlar (KV) | B21: Trade Payables (ST) | C21: 130363030 | D21: 134020121
A22: Kısa Vadeli Borçlanmalar | B22: Short-Term Debt | C22: 115029066 | D22: 67250109
A23: UV Borçların KV Kısmı | B23: Current portion of LT Debt | C23: 32919788 | D23: 14252329
A24: KV Yükümlülükler Toplamı | B24: Total Current Liabilities | C24: 340655670 | D24: 289582799
A25: Uzun Vadeli Borçlanmalar | B25: Long-Term Debt | C25: 87949553 | D25: 99185334
A26: Toplam Yükümlülükler | B26: Total Liabilities | C26: 467626459 | D26: 422340360
A27: Toplam Özkaynaklar | B27: Total Equity | C27: 75905153 | D27: 98252467
A30: Renk Kodu / Color Code:
A31: • Mavi = Sabit girdi / Hardcoded input
A32: • Yeşil = Diğer sayfadan referans / Cross-sheet reference
A33: • Siyah = Bu sayfadaki formül / Local formula

Sheet 2. KPI Hesaplamalari
A1: ARÇELİK A.Ş. — KPI Hesaplamaları / KPI Calculations
A2: Tüm değerler '1. Ham Veri' sayfasından canlı formüllerle hesaplanmıştır
A4: # | B4: KPI Adı / KPI Name | C4: Formül / Formula | D4: 2025 | E4: 2024 | F4: YoY Değişim
A5: 1 | B5: Brüt Kar Marjı (Gross Profit Margin) | C5: Brüt Kar / Hasılat × 100 | D5: ='1. Ham Veri (Raw Data)'!C8/'1. Ham Veri (Raw Data)'!C6 -> 0.28781003 | E5: ='1. Ham Veri (Raw Data)'!D8/'1. Ham Veri (Raw Data)'!D6 -> 0.27558634 | F5: =(D5-E5)*100 -> 1.2224
A6: 2 | B6: Net Kar Marjı (Net Profit Margin) | C6: Net Kar / Hasılat × 100 | D6: ='1. Ham Veri (Raw Data)'!C14/'1. Ham Veri (Raw Data)'!C6 -> -0.018703359 | E6: ='1. Ham Veri (Raw Data)'!D14/'1. Ham Veri (Raw Data)'!D6 -> -0.0051506181 | F6: =(D6-E6)*100 -> -1.3553
B7: İşletme Sermayesi Bileşenleri (Working Capital Cycle Components)
B8: Stok Devir Süresi / DIO | C8: Stoklar / SMM × 365 | D8: ='1. Ham Veri (Raw Data)'!C18/'1. Ham Veri (Raw Data)'!C7*365 -> 88.017303 | E8: ='1. Ham Veri (Raw Data)'!D18/'1. Ham Veri (Raw Data)'!D7*365 -> 84.327163 | F8: =D8-E8 -> 3.6901395
A9: 3 | B9: Alacak Tahsil Süresi / DSO | C9: Tic. Alacaklar / Hasılat × 365 | D9: ='1. Ham Veri (Raw Data)'!C17/'1. Ham Veri (Raw Data)'!C6*365 -> 81.238747 | E9: ='1. Ham Veri (Raw Data)'!D17/'1. Ham Veri (Raw Data)'!D6*365 -> 79.147076 | F9: =D9-E9 -> 2.0916713
B10: Borç Ödeme Süresi / DPO | C10: Tic. Borçlar / SMM × 365 | D10: ='1. Ham Veri (Raw Data)'!C21/'1. Ham Veri (Raw Data)'!C7*365 -> 127.51916 | E10: ='1. Ham Veri (Raw Data)'!D21/'1. Ham Veri (Raw Data)'!D7*365 -> 120.38222 | F10: =D10-E10 -> 7.1369408
A11: 4 | B11: Nakit Dönüşüm Döngüsü / CCC | C11: DIO + DSO − DPO | D11: =D8+D9-D10 -> 41.736891 | E11: =E8+E9-E10 -> 43.09202 | F11: =D11-E11 -> -1.35513
A12: 5 | B12: Ticari Borç Devir Oranı (A/P Turnover) | C12: SMM / Tic. Borçlar | D12: ='1. Ham Veri (Raw Data)'!C7/'1. Ham Veri (Raw Data)'!C21 -> 2.862315 | E12: ='1. Ham Veri (Raw Data)'!D7/'1. Ham Veri (Raw Data)'!D21 -> 3.0320093 | F12: =D12-E12 -> -0.16969427

Sheet 3. Analiz ve Gerekce
A1: KPI Seçim Gerekçeleri ve Bulgular
A2: Her KPI için: ne ölçer, neden seçildi, Arçelik için ne anlama geliyor, ne yapılmalı
A4: # | B4: KPI | C4: Neden Seçildi (Why) | D4: Bulgu ve Aksiyon (Insight & Action)
A5: 1 | B5: Brüt Kar Marjı (Gross Profit Margin) | C5: Hasılatın ne kadarının üretim sonrası kar olarak kaldığını gösterir. Üretim verimliliği ve fiyatlandırma gücünün en temel ölçüsüdür. Kârlılığı iyileştirmek isteyen bir şirket için ilk bakılacak orandır. | D5: Arçelik 2024'te %27.6 → 2025'te %28.8 (+1.2 pp) iyileşme gösterdi. Üretim maliyeti yönetiminde başarı sağlandığını gösteriyor. AKSİYON: Hammadde tedarik anlaşmaları güvence altına alınmalı, ölçek ekonomilerinden yararlanılmalı.
A6: 2 | B6: Net Kar Marjı (Net Profit Margin) | C6: Tüm gider, vergi ve finansman maliyetleri sonrası nihai kârlılığı gösterir. Asıl 'alt çizgi' performans göstergesidir. Brüt kâr iyi olsa bile NPM zarar gösteriyorsa sorun operasyonda değil, OPEX/finansman/vergidedir. | D6: 2024: -%0.52 → 2025: -%1.87 — KÖTÜLEŞTİ ❌ Brüt marj iyileşmesine rağmen net marj kötüleşti. Sebep: 47.6 milyar TL finansman gideri (Türkiye'deki yüksek faiz/enflasyon ortamı). AKSİYON: Kısa vadeli borç yeniden yapılandırılmalı; pazarlama giderleri (hasılatın %19.8'i) gözden geçirilmeli.
A7: 3 | B7: Alacak Tahsil Süresi (DSO) | C7: Müşterilerden parayı kaç günde tahsil ettiğimizi gösterir. Yüksek DSO = nakit alacaklarda kilitli = işletme sermayesi sıkışıklığı. Nakit seviyesini iyileştirmek için doğrudan müdahale edilecek metriklerden biri. | D7: 2024: 79.1 gün → 2025: 81.2 gün (+2.1 gün) — hafif kötüleşme. Yaklaşık 6 milyar TL daha fazla nakit alacaklarda kilitli. AKSİYON: Tahsilat süreçleri sıkılaştırılmalı, erken ödeme indirimi (early payment discount) sunulmalı, kredi politikası gözden geçirilmeli.
A8: 4 | B8: Nakit Dönüşüm Döngüsü (CCC) | C8: DIO + DSO − DPO. Bir liranın stoktan başlayıp tekrar nakit olarak geri dönmesi kaç gün sürüyor? Nakit verimliliğinin özet metriği. Düşük CCC = az işletme sermayesi ihtiyacı = daha çok serbest nakit. | D8: 2024: 43.0 gün → 2025: 41.7 gün (-1.3 gün) — hafif iyileşme ✅ Bileşenler: Stok 88g, Alacak 81g, Borç 127g. AKSİYON: Stok 88 gün çok yüksek (rakip aralığı 60-70 gün); talep tahminleme iyileştirilmeli, JIT envanter uygulanmalı.
A9: 5 | B9: Ticari Borç Devir Oranı (A/P Turnover) | C9: Tedarikçilere yılda kaç kez ödeme yapıldığını gösterir. Düşük oran = uzun ödeme vadesi = nakit daha uzun süre şirkette kalıyor. Çok düşükse tedarikçi ilişkileri zedelenebilir; çok yüksekse vade pazarlık gücü kullanılmıyor demektir. | D9: 2024: 3.03x → 2025: 2.86x — yavaşladı (daha geç ödüyor). Stratejik açıdan: kriz döneminde nakit korumak için tedarikçi vadesi uzatılmış olabilir. AKSİYON: DPO 127 gün (sektör ~80-100 gün); uzun vadede tedarikçi güvenini bozabilir, optimum nokta belirlenmeli.

Sheet 4. Sonuc ve Oneriler
A1: Sonuç ve Stratejik Öneriler
A2: Arçelik A.Ş. — 2024 / 2025 KPI Karşılaştırması
A4: 1. YÖNETİCİ ÖZETİ / EXECUTIVE SUMMARY
A5: Arçelik'in 2025 yılı analizinde, brüt kârlılık (%28.8) ve nakit pozisyonu güçlü (97.8 milyar TL); ancak NET ZARAR derinleşti (-9.8 milyar TL, 2024'te -2.9 milyar TL idi). Bu durumun ana sebebi operasyonel verimsizlik değil, finansman giderleri (47.6 milyar TL) ve yüksek pazarlama maliyetleridir (hasılatın %19.8'i). ÖZET DURUM: Sağlam üretim verimliliğiyle çalışan ama yüksek faiz ortamından dolayı net olarak zarar eden bir şirket görüyoruz. Önemli sinyal: Cari oran 0.97 (1'in altında!) — kısa vadeli yükümlülükleri kısa vadeli varlıklarla karşılayamıyor. Likidite riski mevcut.
A7: 2. KÂRLILIK BULGULARI / PROFITABILITY FINDINGS
A8: ✅ Brüt Marj iyileşti | B8: %27.6 → %28.8 (+1.2 pp). Üretim/maliyet yönetimi başarılı.
A9: ❌ Net Marj kötüleşti | B9: -%0.52 → -%1.87. Brüt kâr finansman giderlerine yenildi.
A10: ⚠️ Faaliyet/Net farkı kritik | B10: Faaliyet kârı 10.5 milyar TL → Net zarar 9.8 milyar TL. Fark (20.3 milyar TL) finansman giderlerinden (47.6 milyar TL) kaynaklanıyor; finansman gelirleri ve diğer kalemler (ham veride yok) bunun bir kısmını dengeliyor.
A11: ⚠️ Pazarlama giderleri yüksek | B11: Hasılatın %19.8'i pazarlamaya gidiyor (104 milyar TL). Sektör ortalamasının üzerinde.
A12: ⚠️ Hasılat düştü | B12: 560.9 → 523.9 milyar TL (−6.6%). Brüt marj iyileşmesi daralan satışlarla birlikte geldi.
A13: 3. NAKİT/LİKİDİTE BULGULARI / CASH & LIQUIDITY FINDINGS
A14: ✅ Nakit pozisyonu güçlendi | B14: 66.5 milyar TL → 97.8 milyar TL (+47%). Likit varlıklar arttı.
A15: ❌ Kısa vadeli borç patladı | B15: 67.3 → 115.0 milyar TL (+71%). Faiz baskısı arttı.
A16: ❌ Cari oran 1'in altında | B16: 330.7 / 340.7 = 0.97. KV varlıklar KV borçları karşılamıyor.
A17: ✅ CCC kısaldı | B17: 43 gün → 41.7 gün. İşletme sermayesi verimliliği biraz iyileşti.
A18: ⚠️ Stok süresi yüksek | B18: 88 gün (sektör ~60-70). 90 milyar TL nakit stoklarda kilitli.
A19: ❌ Net borç ve kaldıraç arttı | B19: Net borç 114.2 → 138.1 milyar TL (+21%); özkaynak 98.3 → 75.9 milyar TL (−23%). Nakit artışı borçla finanse edildi.
A20: 4. ÖNERİLER / RECOMMENDATIONS
A21: 1. Borç yapısını yeniden düzenle | B21: 115 milyar TL'lik KV borcun bir kısmı uzun vadeye dönüştürülmeli. Tahvil ihracı veya sendikasyon kredisi araştırılmalı. Cari oranın 1'in üstüne çıkarılması öncelik.
A22: 2. Pazarlama harcamalarını gözden geçir | B22: Pazarlama hasılatın %19.8'i. ROI analizi yapılmalı; düşük getirili kanallar azaltılıp dijitale yönelim hızlandırılmalı. Hedef: 2 puan azaltma → +10 milyar TL faaliyet kârı.
A23: 3. Stok yönetimini iyileştir | B23: 88 günlük stok süresi sektör ortalamasının üzerinde. Talep tahminleme, JIT envanter ve SKU sadeleştirme ile 70 güne indirme hedeflenmeli. Serbest kalacak nakit: ~18 milyar TL.
A24: 4. Tahsilat süreçlerini sıkılaştır | B24: DSO 81 → 70 güne indirilirse ~16 milyar TL nakit serbest kalır. Erken ödeme indirimi (örn. 2/10 net 30), otomatik fatura, kredi değerlendirme süreçleri.
A25: 5. Kur ve faiz riskini hedge et | B25: Net zararın çoğu finansman kaynaklı. Döviz pozisyonu ve faiz riski için türev araçlarla (forward, swap) hedge stratejisi gözden geçirilmeli.
A27: Hazırlayan: Iryna | Şirket: Arçelik A.Ş. (BIST: ARCLK) | Veri Dönemi: 2024-2025 Yılsonu

Sheet 5. PQ Veri Kaynagi
A1: Power Query Veri Kaynağı / Data Source
A2: Bu tablo Power Query tarafından kullanılmak üzere düz formatta hazırlanmıştır
A4: Item_TR | B4: Item_EN | C4: Year_2025 | D4: Year_2024 | E4: Category
A5: Hasılat | B5: Revenue | C5: 523933321 | D5: 560936754 | E5: Income Statement
A6: Satışların Maliyeti (-) | B6: Cost of Goods Sold (COGS) | C6: 373140054 | D6: 406350247 | E6: Income Statement
A7: Brüt Kar | B7: Gross Profit | C7: 150793267 | D7: 154586507 | E7: Income Statement
A8: Pazarlama Giderleri (-) | B8: Marketing Expenses | C8: 103927285 | D8: 108281560 | E8: Income Statement
A9: Genel Yönetim Giderleri (-) | B9: G&A Expenses | C9: 33379774 | D9: 32435620 | E9: Income Statement
A10: Ar-Ge Giderleri (-) | B10: R&D Expenses | C10: 6490885 | D10: 6346498 | E10: Income Statement
A11: Esas Faaliyet Karı | B11: Operating Profit | C11: 10494106 | D11: 9322710 | E11: Income Statement
A12: Finansman Giderleri (-) | B12: Financing Expenses | C12: 47635992 | D12: 61910541 | E12: Income Statement
A13: Net Dönem Karı / Zararı | B13: Net Income (Loss) | C13: -9799313 | D13: -2889171 | E13: Income Statement
A14: Nakit ve Nakit Benzerleri | B14: Cash & Cash Equivalents | C14: 97829154 | D14: 66514006 | E14: Balance Sheet
A15: Ticari Alacaklar (KV) | B15: Trade Receivables (ST) | C15: 116612840 | D15: 121634257 | E15: Balance Sheet
A16: Stoklar | B16: Inventory | C16: 89980222 | D16: 93880448 | E16: Balance Sheet
... A25: Toplam Özkaynaklar | B25: Total Equity | C25: 75905153 | D25: 98252467 | E25: Balance Sheet
A28: Power Query Talimatları
A29: 1. Excel'de Veri sekmesine git → 'Tablodan/Aralıktan' → tbl_FinancialData seç
A30: 2. Power Query Editor açılır
A31: 3. Year_2025 ve Year_2024 sütunlarını seç → Sağ tık → 'Sütunları Kaldırma Pivotu' (Unpivot)
A32: 4. 'Attribute' sütununu 'Year' olarak yeniden adlandır, 'Value' sütununu 'Amount' yap
A33: 5. Year sütunundan 'Year_' önekini kaldır (Değerleri Değiştir)
A34: 6. Year sütunu türünü Tam Sayı yap
A35: 7. Ana Sayfa → Kapat ve Yükle → Yeni sayfaya yükle
A37: → Sonuç: 42 satırlık tek bir uzun tablo (her satır = bir kalem-yıl kombinasyonu)
A38: → Result: 42-row long table (each row = one item-year combination)
